cordage/__about__.py
cordage/__init__.py
cordage/context.py
cordage/exceptions.py
cordage/experiment.py
cordage/global_config.py
cordage/metadata.py
cordage/util.py
cordage-0.0.13.dist-info/METADATA
cordage-0.0.13.dist-info/WHEEL
cordage-0.0.13.dist-info/licenses/LICENSE
cordage-0.0.13.dist-info/RECORD
