Metadata-Version: 2.4
Name: cordage
Version: 0.0.13
Summary: Computational research data management tool
Project-URL: Documentation, https://plonerma.github.io/cordage/
Project-URL: Issues, https://github.com/plonerma/cordage/issues
Project-URL: Source, https://github.com/plonerma/cordage
Author-email: Max Ploner <cordage@maxploner.de>
License-Expression: MIT
License-File: LICENSE
Classifier: Development Status :: 3 - Alpha
Classifier: License :: OSI Approved :: MIT License
Classifier: Operating System :: OS Independent
Classifier: Programming Language :: Python
Classifier: Programming Language :: Python :: 3.9
Classifier: Programming Language :: Python :: 3.10
Classifier: Programming Language :: Python :: 3.11
Classifier: Programming Language :: Python :: 3.12
Classifier: Programming Language :: Python :: 3.13
Requires-Python: >=3.9
Requires-Dist: colorlog
Requires-Dist: dacite
Requires-Dist: docstring-parser
Provides-Extra: toml
Requires-Dist: toml; extra == 'toml'
Provides-Extra: yaml
Requires-Dist: pyyaml; extra == 'yaml'
